cevir/__init__.py
cevir/examples.py
cevir-1.0.0.dist-info/LICENCE
cevir-1.0.0.dist-info/METADATA
cevir-1.0.0.dist-info/WHEEL
cevir-1.0.0.dist-info/top_level.txt
cevir-1.0.0.dist-info/RECORD
