Metadata-Version: 2.1
Name: cevir
Version: 1.0.0
Summary: A small step for me but a huge step for Turkish Python Lovers
Author-email: xalilcan47 <programlamadunyam@gmail.com>
Project-URL: Homepage, https://github.com/hackedubuntu/cevir
Project-URL: Bug Tracker, https://github.com/hackedubuntu/cevir/issues
Classifier: Programming Language :: Python :: 3
Classifier: License :: OSI Approved :: MIT License
Classifier: Operating System :: OS Independent
Requires-Python: >=3.5
License-File: LICENCE
